splinebox/__init__.py
splinebox/_version.py
splinebox/basis_functions.py
splinebox/spline_curves.py
splinebox-0.5.1.dist-info/licenses/LICENSE
splinebox-0.5.1.dist-info/METADATA
splinebox-0.5.1.dist-info/WHEEL
splinebox-0.5.1.dist-info/top_level.txt
splinebox-0.5.1.dist-info/RECORD
