Metadata-Version: 2.4
Name: splinebox
Version: 0.5.1
Summary: A python package for fitting splines.
Author-email: Florian Aymanns <florian.aymanns@epfl.ch>, Virginie Uhlmann <uhlmann@ebi.ac.uk>, Edward Andò <edward.ando@epfl.ch>
Maintainer-email: Florian Aymanns <flroian.aymanns@epfl.ch>
License: BSD 3-Clause License
Project-URL: Repository, https://github.com/EPFL-Center-for-Imaging/splinebox
Keywords: splines
Classifier: Development Status :: 5 - Production/Stable
Classifier: Intended Audience :: Developers
Classifier: License :: OSI Approved :: BSD License
Classifier: Operating System :: OS Independent
Classifier: Programming Language :: Python
Classifier: Programming Language :: Python :: 3
Classifier: Programming Language :: Python :: 3 :: Only
Classifier: Programming Language :: Python :: 3.8
Classifier: Programming Language :: Python :: 3.9
Classifier: Programming Language :: Python :: 3.10
Classifier: Programming Language :: Python :: 3.11
Classifier: Programming Language :: Python :: 3.12
Classifier: Topic :: Scientific/Engineering
Requires-Python: >=3.8
License-File: LICENSE
Requires-Dist: numpy
Requires-Dist: scipy
Requires-Dist: numba
Provides-Extra: test
Requires-Dist: tox; extra == "test"
Requires-Dist: pytest; extra == "test"
Requires-Dist: pytest-cov; extra == "test"
Provides-Extra: examples
Requires-Dist: matplotlib; extra == "examples"
Requires-Dist: scikit-image; extra == "examples"
Requires-Dist: pandas; extra == "examples"
Requires-Dist: seaborn; extra == "examples"
Provides-Extra: docs
Requires-Dist: splinebox[examples]; extra == "docs"
Requires-Dist: sphinx-gallery; extra == "docs"
Requires-Dist: pydata-sphinx-theme; extra == "docs"
Requires-Dist: sphinx-design; extra == "docs"
Requires-Dist: pyvista[jupyter]; extra == "docs"
Requires-Dist: skan; extra == "docs"
Provides-Extra: all
Requires-Dist: splinebox[docs,examples,test]; extra == "all"
Dynamic: license-file
